solr2es
