Metadata-Version: 1.1
Name: solr2es
Version: 0.6
Summary: Python solr/elasticsearch migration script
Home-page: https://github.com/ICIJ/solr2es
Author: Anne L'Hôte, Bruno Thomas
Author-email: alhote@icij.org, bthomas@icij.org
License: GPL-3.0
Keywords: migration search engine solr elasticsearch
Platform: UNKNOWN
Classifier: Programming Language :: Python
Classifier: Programming Language :: Python :: 3.6
